runml_infuse/__init__.py
runml_infuse/base.py
runml_infuse/datasets.py
runml_infuse/version.py
runml_infuse/ad/__init__.py
runml_infuse/ad/adversarialae.py
runml_infuse/ad/model_distillation.py
runml_infuse/cd/__init__.py
runml_infuse/cd/_domain_clf.py
runml_infuse/cd/base.py
runml_infuse/cd/base_online.py
runml_infuse/cd/chisquare.py
runml_infuse/cd/classifier.py
runml_infuse/cd/context_aware.py
runml_infuse/cd/cvm.py
runml_infuse/cd/cvm_online.py
runml_infuse/cd/fet.py
runml_infuse/cd/fet_online.py
runml_infuse/cd/ks.py
runml_infuse/cd/learned_kernel.py
runml_infuse/cd/lsdd.py
runml_infuse/cd/lsdd_online.py
runml_infuse/cd/mmd.py
runml_infuse/cd/mmd_online.py
runml_infuse/cd/model_uncertainty.py
runml_infuse/cd/preprocess.py
runml_infuse/cd/spot_the_diff.py
runml_infuse/cd/tabular.py
runml_infuse/cd/utils.py
runml_infuse/cd/pytorch/__init__.py
runml_infuse/cd/pytorch/classifier.py
runml_infuse/cd/pytorch/context_aware.py
runml_infuse/cd/pytorch/learned_kernel.py
runml_infuse/cd/pytorch/lsdd.py
runml_infuse/cd/pytorch/lsdd_online.py
runml_infuse/cd/pytorch/mmd.py
runml_infuse/cd/pytorch/mmd_online.py
runml_infuse/cd/pytorch/preprocess.py
runml_infuse/cd/pytorch/spot_the_diff.py
runml_infuse/cd/pytorch/utils.py
runml_infuse/cd/sklearn/__init__.py
runml_infuse/cd/sklearn/classifier.py
runml_infuse/cd/tensorflow/__init__.py
runml_infuse/cd/tensorflow/classifier.py
runml_infuse/cd/tensorflow/context_aware.py
runml_infuse/cd/tensorflow/learned_kernel.py
runml_infuse/cd/tensorflow/lsdd.py
runml_infuse/cd/tensorflow/lsdd_online.py
runml_infuse/cd/tensorflow/mmd.py
runml_infuse/cd/tensorflow/mmd_online.py
runml_infuse/cd/tensorflow/preprocess.py
runml_infuse/cd/tensorflow/spot_the_diff.py
runml_infuse/cd/tensorflow/utils.py
runml_infuse/models/__init__.py
runml_infuse/models/pytorch/__init__.py
runml_infuse/models/pytorch/embedding.py
runml_infuse/models/pytorch/trainer.py
runml_infuse/models/tensorflow/__init__.py
runml_infuse/models/tensorflow/autoencoder.py
runml_infuse-0.9.1.dev0.dist-info/LICENSE
runml_infuse-0.9.1.dev0.dist-info/METADATA
runml_infuse-0.9.1.dev0.dist-info/WHEEL
runml_infuse-0.9.1.dev0.dist-info/top_level.txt
runml_infuse-0.9.1.dev0.dist-info/RECORD
