Metadata-Version: 2.1
Name: runml-infuse
Version: 0.9.1.dev0
Summary: Algorithms for outlier detection, concept drift and metrics.
Home-page: https://github.com/SeldonIO/runml-infuse
Author: Seldon Technologies Ltd.
Author-email: hello@seldon.io
License: Apache 2.0
Platform: UNKNOWN
Classifier: Intended Audience :: Science/Research
Classifier: Operating System :: OS Independent
Classifier: Programming Language :: Python :: 3
Classifier: Programming Language :: Python :: 3.7
Classifier: Programming Language :: Python :: 3.8
Classifier: Programming Language :: Python :: 3.9
Classifier: License :: OSI Approved :: Apache Software License
Classifier: Topic :: Scientific/Engineering
Requires-Python: >=3.7
License-File: LICENSE
Requires-Dist: matplotlib (<4.0.0,>=3.0.0)
Requires-Dist: numpy (<2.0.0,>=1.16.2)
Requires-Dist: pandas (<2.0.0,>=0.23.3)
Requires-Dist: Pillow (<10.0.0,>=5.4.1)
Requires-Dist: opencv-python (<5.0.0,>=3.2.0)
Requires-Dist: scipy (<2.0.0,>=1.3.0)
Requires-Dist: scikit-image (!=0.17.1,<0.20,>=0.14.2)
Requires-Dist: scikit-learn (<1.1.0,>=0.20.2)
Requires-Dist: tensorflow (!=2.6.0,!=2.6.1,<2.9.0,>=2.2.0)
Requires-Dist: tensorflow-probability (<0.13.0,>=0.8.0)
Requires-Dist: transformers (<5.0.0,>=4.0.0)
Requires-Dist: dill (<0.4.0,>=0.3.0)
Requires-Dist: tqdm (<5.0.0,>=4.28.1)
Requires-Dist: requests (<3.0.0,>=2.21.0)
Requires-Dist: numba (!=0.54.0,<0.56.0,>=0.50.0)
Provides-Extra: prophet
Requires-Dist: fbprophet (<0.7,>=0.5) ; extra == 'prophet'
Requires-Dist: holidays (==0.9.11) ; extra == 'prophet'
Requires-Dist: pystan (<3.0) ; extra == 'prophet'
Provides-Extra: torch
Requires-Dist: torch (>=1.7.0) ; extra == 'torch'
